MANIFEST.in
README.md
README.rst
setup.cfg
setup.py
dryxDropboxCL/.coverage
dryxDropboxCL/__init__.py
dryxDropboxCL/__init__.pyc
dryxDropboxCL/__version__.py
dryxDropboxCL/cl_utils.py
dryxDropboxCL/cl_utils.pyc
dryxDropboxCL/setup.cfg
dryxDropboxCL/setup_selective_sync.py
dryxDropboxCL/setup_selective_sync.pyc
dryxDropboxCL/start_if_not_running.py
dryxDropboxCL/start_if_not_running.pyc
dryxDropboxCL/utKit.py
dryxDropboxCL/utKit.pyc
dryxDropboxCL.egg-info/PKG-INFO
dryxDropboxCL.egg-info/SOURCES.txt
dryxDropboxCL.egg-info/dependency_links.txt
dryxDropboxCL.egg-info/entry_points.txt
dryxDropboxCL.egg-info/not-zip-safe
dryxDropboxCL.egg-info/requires.txt
dryxDropboxCL.egg-info/top_level.txt
dryxDropboxCL/commonutils/__init__.py
dryxDropboxCL/commonutils/__init__.pyc
dryxDropboxCL/commonutils/getpackagepath.py
dryxDropboxCL/commonutils/getpackagepath.pyc
dryxDropboxCL/original/__init__.py
dryxDropboxCL/original/__init__.pyc
dryxDropboxCL/original/dropbox.py
dryxDropboxCL/original/dropbox.pyc
dryxDropboxCL/original/tests/__init__.py
dryxDropboxCL/original/tests/__init__.pyc
dryxDropboxCL/original/tests/test_dropbox.py
dryxDropboxCL/original/tests/test_dropbox.pyc
dryxDropboxCL/tests/__init__.pyc
dryxDropboxCL/tests/test_cl_utils.py
dryxDropboxCL/tests/test_cl_utils.pyc
dryxDropboxCL/tests/test_setup_selective_sync.py
dryxDropboxCL/tests/test_setup_selective_sync.pyc
dryxDropboxCL/tests/test_start_if_not_running.py
dryxDropboxCL/tests/test_start_if_not_running.pyc
dryxDropboxCL/tests/input/general_settings.yaml
dryxDropboxCL/tests/output/.DS_Store
dryxDropboxCL/tests/output/nosetest_debug.log