Metadata-Version: 1.1
Name: dryxDropboxCL
Version: 0.1.2
Summary: Extra helper tools for the dropbox command-line
Home-page: https://github.com/thespacedoctor/dryxDropboxCL
Author: David Young
Author-email: davidrobertyoung@gmail.com
License: MIT
Download-URL: https://github.com/thespacedoctor/dryxDropboxCL/archive/v0.1.2.zip
Keywords: dropbox, tools
Platform: UNKNOWN
Classifier: Development Status :: 4 - Beta
Classifier: License :: OSI Approved :: MIT License
Classifier: Programming Language :: Python :: 2.7
Classifier: Topic :: Utilities
